mater/__init__.py
mater/_bio_physical.py
mater/_non_physical.py
mater/_pre_processing.py
mater/_utils.py
mater/_variable_classes.py
mater/model.py
mater-0.14.2.dist-info/METADATA
mater-0.14.2.dist-info/WHEEL
mater-0.14.2.dist-info/licenses/LICENSE
mater-0.14.2.dist-info/RECORD
