Metadata-Version: 2.4
Name: mater
Version: 0.14.2
Summary: Multi-regional Assessment of Technologies, Energy and Resources
Project-URL: Documentation, https://isterre-dynamic-modeling.gricad-pages.univ-grenoble-alpes.fr/mater-project/mater/
Project-URL: repository, https://gricad-gitlab.univ-grenoble-alpes.fr/isterre-dynamic-modeling/mater-project/mater
Author-email: francois-verzier <francois.verzier@univ-grenoble-alpes.fr>, Lauranne Sarribouette <lauranne.sarribouette@univ-grenoble-alpes.fr>
License:                    GNU LESSER GENERAL PUBLIC LICENSE
License-File: LICENSE
Keywords: ecological,energy,materials,research,scientific
Classifier: Development Status :: 3 - Alpha
Classifier: Environment :: Console
Classifier: Intended Audience :: Science/Research
Classifier: License :: OSI Approved :: GNU Lesser General Public License v3 (LGPLv3)
Classifier: Operating System :: OS Independent
Classifier: Programming Language :: Python
Classifier: Programming Language :: Python :: 3.10
Classifier: Programming Language :: Python :: 3.11
Classifier: Programming Language :: Python :: 3.12
Classifier: Programming Language :: Python :: 3.13
Classifier: Programming Language :: Python :: 3.14
Classifier: Topic :: Scientific/Engineering
Requires-Python: <4.0,>=3.10
Requires-Dist: data-completion-tool>=0.3.2
Requires-Dist: openpyxl>=3.1.5
Requires-Dist: pandas>=2.2.3
Requires-Dist: pyarrow>=18.1.0
Requires-Dist: tqdm>=4.67.1
Requires-Dist: xlrd>=2.0.1
